pytest_ldap/__init__.py
pytest_ldap-0.0.1.dist-info/LICENSE.md
pytest_ldap-0.0.1.dist-info/METADATA
pytest_ldap-0.0.1.dist-info/WHEEL
pytest_ldap-0.0.1.dist-info/entry_points.txt
pytest_ldap-0.0.1.dist-info/top_level.txt
pytest_ldap-0.0.1.dist-info/RECORD
